trac_optimizer/__init__.py
trac_optimizer/trac.py
trac_optimizer/experimental/jax/trac.py
trac_optimizer-0.0.2.dist-info/METADATA
trac_optimizer-0.0.2.dist-info/WHEEL
trac_optimizer-0.0.2.dist-info/licenses/LICENSE
trac_optimizer-0.0.2.dist-info/RECORD
