Metadata-Version: 2.3
Name: trac_optimizer
Version: 0.0.2
Summary: Official implementation of the TRAC optimizer in Fast TRAC: A Parameter-Free Optimizer for Lifelong Reinforcement Learning.
Project-URL: Homepage, https://computationalrobotics.seas.harvard.edu/TRAC/
Project-URL: Issues, https://github.com/ComputationalRobotics/TRAC/issues
Author-email: Aneesh Muppidi <aneeshmuppidi@college.harvard.edu>
License-File: LICENSE
Classifier: License :: OSI Approved :: MIT License
Classifier: Operating System :: OS Independent
Classifier: Programming Language :: Python :: 3
Requires-Python: >=3.8
